[{"input":"5LP","Damage":"300","Startup":"4","Active":"4","Recovery":"7","Total":"14","Hit_Adv":"5","Block_Adv":"-2","Guard":"LH","Cancel":"Chn Sp SA","Hitconfirm":"14","Dmg_Scaling":"10% Starter","Punish_Adv":"9","PerfParry_Adv":"-9","DR_Cancel_onHit":"4","DR_Cancel_onBlock":"-3","Hitstun":"16","Blockstun":"9","Hitstop":"9","DriveDmg_Block":"500","DriveDmg_Hit[PC]":"[2000]","Drive_Gain":"250","SuperGain_Hit":"300 (210)","SuperGain_Block":"150 (75)","Invuln":"-","Armor":"-","Airborne":"-","Juggle_Start":"-","Juggle_Increase":"-","Juggle_Limit":"-","Notes":"Chains into 5LP\/2LP\/2LK; high active frame count makes it a useful meaty (up to 8\/1); SA2 cancel: 8\/1; DR cancel is delayed until after 3rd active frame","Chip":null},{"input":"5LP (FSE Chain)","Damage":"100","Startup":"4","Active":"4","Recovery":"7","Total":"14","Hit_Adv":"5","Block_Adv":"-2","Guard":"LH","Cancel":"Chn Sp SA","Hitconfirm":"14 Sp \/ 16 Chn","Dmg_Scaling":"10% Starter","Punish_Adv":"9","PerfParry_Adv":"-9","DR_Cancel_onHit":"4","DR_Cancel_onBlock":"-3","Hitstun":"16","Blockstun":"9","Hitstop":"9","DriveDmg_Block":"125","DriveDmg_Hit[PC]":"[500]","Drive_Gain":"62","SuperGain_Hit":"-","SuperGain_Block":"-","Invuln":"-","Armor":"-","Airborne":"-","Juggle_Start":"-","Juggle_Increase":"1","Juggle_Limit":"-","Notes":"Chained version during SA2 (FSE); maintains juggle state vs. airborne opponents; DR cancel is delayed until after 3rd active frame","Chip":null},{"input":"5MP","Damage":"600","Startup":"6","Active":"4","Recovery":"12","Total":"21","Hit_Adv":"7","Block_Adv":"2","Guard":"LH","Cancel":"Sp SA TC","Hitconfirm":"16","Dmg_Scaling":"-","Punish_Adv":"11","PerfParry_Adv":"-14","DR_Cancel_onHit":"12","DR_Cancel_onBlock":"7","Hitstun":"23","Blockstun":"18","Hitstop":"11","DriveDmg_Block":"3000","DriveDmg_Hit[PC]":"[4000]","Drive_Gain":"1500","SuperGain_Hit":"500 (350)","SuperGain_Block":"250 (125)","Invuln":"-","Armor":"-","Airborne":"-","Juggle_Start":"-","Juggle_Increase":"-","Juggle_Limit":"-","Notes":"Strong combo\/pressure starter and meaty tool, especially out of Drive Rush to minimize pushback; meaty timing can be up to 10\/5; SA2 cancel: 14\/9; special\/DR cancel is delayed until after 2nd active frame","Chip":null},{"input":"5MP (FSE Chain)","Damage":"400","Startup":"6","Active":"4","Recovery":"12","Total":"21","Hit_Adv":"7","Block_Adv":"2","Guard":"LH","Cancel":"Chn Sp SA","Hitconfirm":"16 Sp \/ 18 Chn","Dmg_Scaling":"-","Punish_Adv":"11","PerfParry_Adv":"-14","DR_Cancel_onHit":"12","DR_Cancel_onBlock":"7","Hitstun":"23","Blockstun":"18","Hitstop":"9","DriveDmg_Block":"750","DriveDmg_Hit[PC]":"[1000]","Drive_Gain":"375","SuperGain_Hit":"-","SuperGain_Block":"-","Invuln":"-","Armor":"-","Airborne":"-","Juggle_Start":"-","Juggle_Increase":"1","Juggle_Limit":"-","Notes":"Chained version during SA2 (FSE); maintains juggle state vs. airborne opponents; 2f shorter hitconfirm window when chained into; special\/DR cancel is delayed until after 2nd active frame","Chip":null},{"input":"5HP","Damage":"800","Startup":"10","Active":"3","Recovery":"24","Total":"36","Hit_Adv":"-1","Block_Adv":"-5","Guard":"LH","Cancel":"Sp SA","Hitconfirm":"17","Dmg_Scaling":"-","Punish_Adv":"3","PerfParry_Adv":"-25","DR_Cancel_onHit":"16","DR_Cancel_onBlock":"12","Hitstun":"26","Blockstun":"22","Hitstop":"13","DriveDmg_Block":"5000","DriveDmg_Hit[PC]":"[8000]","Drive_Gain":"2000","SuperGain_Hit":"1000 (700)","SuperGain_Block":"500 (250)","Invuln":"-","Armor":"-","Airborne":"-","Juggle_Start":"-","Juggle_Increase":"-","Juggle_Limit":"-","Notes":"Forces stand on hit; good whiff punish tool with long range; large hurtbox makes it weak as an anti-air; SA2 cancel: 18\/14","Chip":null},{"input":"5HP (FSE Chain)","Damage":"600","Startup":"10","Active":"3","Recovery":"24","Total":"36","Hit_Adv":"KD 29","Block_Adv":"-5","Guard":"LH","Cancel":"Chn Sp SA","Hitconfirm":"17 Sp \/ 19 Chn","Dmg_Scaling":"-","Punish_Adv":"KD 29","PerfParry_Adv":"-25","DR_Cancel_onHit":"KD 46","DR_Cancel_onBlock":"12","Hitstun":"-","Blockstun":"22","Hitstop":"12","DriveDmg_Block":"1250","DriveDmg_Hit[PC]":"[2000]","Drive_Gain":"500","SuperGain_Hit":"-","SuperGain_Block":"-","Invuln":"-","Armor":"-","Airborne":"-","Juggle_Start":"-","Juggle_Increase":"1","Juggle_Limit":"-","Notes":"Chained version during SA2 (FSE); forces stand on hit; maintains juggle state vs. airborne opponents; 1f shorter hitconfirm window when chained into","Chip":null},{"input":"5LK","Damage":"300","Startup":"5","Active":"3","Recovery":"9","Total":"16","Hit_Adv":"2","Block_Adv":"-3","Guard":"LH","Cancel":"Sp SA","Hitconfirm":"13","Dmg_Scaling":"10% Starter","Punish_Adv":"6","PerfParry_Adv":"-10","DR_Cancel_onHit":"4","DR_Cancel_onBlock":"-1","Hitstun":"13","Blockstun":"7","Hitstop":"9","DriveDmg_Block":"500","DriveDmg_Hit[PC]":"[2000]","Drive_Gain":"250","SuperGain_Hit":"300 (210)","SuperGain_Block":"150 (75)","Invuln":"-","Armor":"-","Airborne":"-","Juggle_Start":"-","Juggle_Increase":"-","Juggle_Limit":"-","Notes":"Good range for a light normal, but can't combo into 214MK; SA2 cancel: 5\/0; special cancel is delayed until after 2nd active frame","Chip":null},{"input":"5LK (FSE Chain)","Damage":"100","Startup":"5","Active":"3","Recovery":"9","Total":"16","Hit_Adv":"2","Block_Adv":"-3","Guard":"LH","Cancel":"Chn Sp SA","Hitconfirm":"13 Sp \/ 15 Chn","Dmg_Scaling":"10% Starter","Punish_Adv":"6","PerfParry_Adv":"-10","DR_Cancel_onHit":"4","DR_Cancel_onBlock":"-1","Hitstun":"13","Blockstun":"7","Hitstop":"9","DriveDmg_Block":"125","DriveDmg_Hit[PC]":"[500]","Drive_Gain":"62","SuperGain_Hit":"-","SuperGain_Block":"-","Invuln":"-","Armor":"-","Airborne":"-","Juggle_Start":"-","Juggle_Increase":"1","Juggle_Limit":"-","Notes":"Chained version during SA2 (FSE); maintains juggle state vs. airborne opponents; special cancel is delayed until after 2nd active frame","Chip":null},{"input":"5MK","Damage":"400,300 (700)","Startup":"5(8)","Active":"2(1)3","Recovery":"17","Total":"27","Hit_Adv":"3","Block_Adv":"-4","Guard":"LH","Cancel":"Sp SA (1st)","Hitconfirm":"14","Dmg_Scaling":"-","Punish_Adv":"7","PerfParry_Adv":"-21 \/ -18","DR_Cancel_onHit":"17","DR_Cancel_onBlock":"5","Hitstun":"27,23","Blockstun":"15,16","Hitstop":"11,11","DriveDmg_Block":"2000x2","DriveDmg_Hit[PC]":"[3000x2]","Drive_Gain":"1000x2","SuperGain_Hit":"350,700 (245,490)","SuperGain_Block":"175,350 (87,175)","Invuln":"-","Armor":"-","Airborne":"-","Juggle_Start":"-","Juggle_Increase":"-","Juggle_Limit":"-","Notes":"8f startup for 2nd hit only; 1st hit can combo from 5LP and has enough hitstun to combo to 214HK for a launch and Fuha stock; great poke in neutral (1st hit can interrupt opponent's button while 2nd hit extends for long range); very effective when used out of Drive Rush; SA2 cancel: 19\/7 (1st hit)","Chip":null},{"input":"5MK (FSE Chain)","Damage":"300,200","Startup":"5(8)","Active":"2(1)3","Recovery":"17","Total":"27","Hit_Adv":"3","Block_Adv":"-4","Guard":"LH","Cancel":"Chn Sp SA","Hitconfirm":"29(15) Sp \/ 31(17) Chn","Dmg_Scaling":"-","Punish_Adv":"7","PerfParry_Adv":"-21 \/ -18","DR_Cancel_onHit":"13 \/ 13","DR_Cancel_onBlock":"5 \/ 6","Hitstun":"23,23","Blockstun":"15,16","Hitstop":"9,9","DriveDmg_Block":"500x2","DriveDmg_Hit[PC]":"[750x2]","Drive_Gain":"250x2","SuperGain_Hit":"-","SuperGain_Block":"-","Invuln":"-","Armor":"-","Airborne":"-","Juggle_Start":"-","Juggle_Increase":"1","Juggle_Limit":"-","Notes":"Chained version during SA2 (FSE); 1st hit has 4f less hitstun (cannot combo into 214HK); when chained into, 4f shorter hitconfirm window (2f if 2nd hit only); maintains juggle state vs. airborne opponents","Chip":null},{"input":"5HK","Damage":"900","Startup":"17","Active":"4","Recovery":"19","Total":"39","Hit_Adv":"2(5)","Block_Adv":"-3(0)","Guard":"LH","Cancel":"-","Hitconfirm":"-","Dmg_Scaling":"20% Starter","Punish_Adv":"KD 42(45) Launch","PerfParry_Adv":"-21(-18)","DR_Cancel_onHit":"-","DR_Cancel_onBlock":"-","Hitstun":"25","Blockstun":"20","Hitstop":"13","DriveDmg_Block":"6000","DriveDmg_Hit[PC]":"[10000]","Drive_Gain":"3000","SuperGain_Hit":"1000 (700)","SuperGain_Block":"500 (250)","Invuln":"-","Armor":"-","Airborne":"-","Juggle_Start":"-","Juggle_Increase":"-","Juggle_Limit":"-","Notes":"Not airborne despite the animation; long range and safe on block with a follow-up juggle on Punish Counter makes it great in neutral; better frame advantage when well spaced (very difficult to connect with the final active frame)","Chip":null},{"input":"5HK (FSE Chain)","Damage":"700","Startup":"17","Active":"4","Recovery":"19","Total":"39","Hit_Adv":"KD 34","Block_Adv":"-3","Guard":"LH","Cancel":"Chn Sp SA","Hitconfirm":"26 Sp\/Chn (PC: 38)","Dmg_Scaling":"20% Starter","Punish_Adv":"KD 34","PerfParry_Adv":"-21","DR_Cancel_onHit":"7 (KD 39)","DR_Cancel_onBlock":"2","Hitstun":"-","Blockstun":"20","Hitstop":"11","DriveDmg_Block":"1500","DriveDmg_Hit[PC]":"[2500]","Drive_Gain":"750","SuperGain_Hit":"-","SuperGain_Block":"-","Invuln":"-","Armor":"-","Airborne":"-","Juggle_Start":"-","Juggle_Increase":"-","Juggle_Limit":"-","Notes":"Becomes fully cancelable during FSE, even when not chained into; not airborne despite the animation; maintains juggle state vs. airborne opponents; 2f shorter hitconfirm window when chained into; special\/DR cancel is delayed until after 5th recovery frame","Chip":null},{"input":"2LP","Damage":"300","Startup":"4","Active":"3","Recovery":"8","Total":"14","Hit_Adv":"4","Block_Adv":"-1","Guard":"LH","Cancel":"Chn Sp SA","Hitconfirm":"13","Dmg_Scaling":"10% Starter","Punish_Adv":"8","PerfParry_Adv":"-9","DR_Cancel_onHit":"4","DR_Cancel_onBlock":"-1","Hitstun":"15","Blockstun":"10","Hitstop":"9","DriveDmg_Block":"500","DriveDmg_Hit[PC]":"[2000]","Drive_Gain":"250","SuperGain_Hit":"300 (210)","SuperGain_Block":"150 (75)","Invuln":"-","Armor":"-","Airborne":"-","Juggle_Start":"-","Juggle_Increase":"-","Juggle_Limit":"-","Notes":"Chains into 5LP\/2LP\/2LK; SA2 cancel: 7\/2; DR cancel is delayed until after 2nd active frame","Chip":null},{"input":"2LP (FSE Chain)","Damage":"100","Startup":"4","Active":"3","Recovery":"8","Total":"14","Hit_Adv":"4","Block_Adv":"-1","Guard":"LH","Cancel":"Chn Sp SA","Hitconfirm":"13 Sp \/ 15 Chn","Dmg_Scaling":"10% Starter","Punish_Adv":"8","PerfParry_Adv":"-9","DR_Cancel_onHit":"4","DR_Cancel_onBlock":"-1","Hitstun":"15","Blockstun":"10","Hitstop":"9","DriveDmg_Block":"125","DriveDmg_Hit[PC]":"[500]","Drive_Gain":"62","SuperGain_Hit":"-","SuperGain_Block":"-","Invuln":"-","Armor":"-","Airborne":"-","Juggle_Start":"-","Juggle_Increase":"-","Juggle_Limit":"-","Notes":"Chained version during SA2 (FSE); maintains juggle state vs. airborne opponents; DR cancel is delayed until after 2nd active frame","Chip":null},{"input":"2MP","Damage":"600","Startup":"6","Active":"4","Recovery":"14","Total":"23","Hit_Adv":"5","Block_Adv":"-2","Guard":"LH","Cancel":"Sp SA","Hitconfirm":"16","Dmg_Scaling":"-","Punish_Adv":"9","PerfParry_Adv":"-16","DR_Cancel_onHit":"13","DR_Cancel_onBlock":"6","Hitstun":"23","Blockstun":"16","Hitstop":"11","DriveDmg_Block":"3000","DriveDmg_Hit[PC]":"[4000]","Drive_Gain":"1500","SuperGain_Hit":"500 (350)","SuperGain_Block":"250 (125)","Invuln":"-","Armor":"-","Airborne":"-","Juggle_Start":"-","Juggle_Increase":"-","Juggle_Limit":"-","Notes":"Good combo tool and useful when buffered in neutral; good anti-air for horizontal approaches (hitbox is above her extended fist); SA2 cancel: 15\/8","Chip":null},{"input":"2MP (FSE Chain)","Damage":"400","Startup":"6","Active":"4","Recovery":"14","Total":"23","Hit_Adv":"5","Block_Adv":"-2","Guard":"LH","Cancel":"Chn Sp SA","Hitconfirm":"16 Sp \/ 18 Chn","Dmg_Scaling":"-","Punish_Adv":"9","PerfParry_Adv":"-16","DR_Cancel_onHit":"13","DR_Cancel_onBlock":"6","Hitstun":"23","Blockstun":"16","Hitstop":"9","DriveDmg_Block":"750","DriveDmg_Hit[PC]":"[1000]","Drive_Gain":"375","SuperGain_Hit":"-","SuperGain_Block":"-","Invuln":"-","Armor":"-","Airborne":"-","Juggle_Start":"-","Juggle_Increase":"-","Juggle_Limit":"-","Notes":"Chained version during SA2 (FSE); maintains juggle state vs. airborne opponents; 2f shorter hitconfirm window when chained into","Chip":null},{"input":"2HP","Damage":"900","Startup":"8","Active":"4","Recovery":"23","Total":"34","Hit_Adv":"3","Block_Adv":"-11","Guard":"LH","Cancel":"Sp SA","Hitconfirm":"18","Dmg_Scaling":"-","Punish_Adv":"7","PerfParry_Adv":"-25","DR_Cancel_onHit":"20","DR_Cancel_onBlock":"6","Hitstun":"30","Blockstun":"16","Hitstop":"13","DriveDmg_Block":"5000","DriveDmg_Hit[PC]":"[8000]","Drive_Gain":"2000","SuperGain_Hit":"1000 (700)","SuperGain_Block":"500 (250)","Invuln":"-","Armor":"-","Airborne":"-","Juggle_Start":"-","Juggle_Increase":"-","Juggle_Limit":"-","Notes":"Forces stand on hit; great anti-air but cannot hit cross-up (upward leg hurtbox is anti-air invincible on frames 8-15); all active frames are cancelable; powerful combo starter after a canceled Drive Rush hitconfirm; SA2 cancel: 22\/8","Chip":null},{"input":"2HP (FSE Chain)","Damage":"700","Startup":"8","Active":"4","Recovery":"23","Total":"34","Hit_Adv":"KD 34","Block_Adv":"-11","Guard":"LH","Cancel":"Sp SA Jmp","Hitconfirm":"16 Sp \/ 18 Jmp \/ 20 Chn","Dmg_Scaling":"-","Punish_Adv":"KD 34","PerfParry_Adv":"-25","DR_Cancel_onHit":"KD 51","DR_Cancel_onBlock":"6","Hitstun":"-","Blockstun":"16","Hitstop":"11","DriveDmg_Block":"1250","DriveDmg_Hit[PC]":"[2000]","Drive_Gain":"750","SuperGain_Hit":"-","SuperGain_Block":"-","Invuln":"-","Armor":"-","Airborne":"-","Juggle_Start":"-","Juggle_Increase":"-","Juggle_Limit":"-","Notes":"Chained version of 2HP during SA2 (FSE); jump cancelable on hit only; when jump canceled, FSE air normals cause juggle state; 2f shorter CHAIN react window when chained into","Chip":null},{"input":"2LK","Damage":"200","Startup":"5","Active":"3","Recovery":"8","Total":"15","Hit_Adv":"3","Block_Adv":"-1","Guard":"L","Cancel":"Chn","Hitconfirm":"-","Dmg_Scaling":"10% Starter","Punish_Adv":"7","PerfParry_Adv":"-9","DR_Cancel_onHit":"-","DR_Cancel_onBlock":"-","Hitstun":"14","Blockstun":"10","Hitstop":"9","DriveDmg_Block":"500","DriveDmg_Hit[PC]":"[2000]","Drive_Gain":"250","SuperGain_Hit":"300 (210)","SuperGain_Block":"150 (75)","Invuln":"-","Armor":"-","Airborne":"-","Juggle_Start":"-","Juggle_Increase":"-","Juggle_Limit":"-","Notes":"Chains into 5LP\/2LP\/2LK; becomes fully cancelable during Feng Shui Engine","Chip":null},{"input":"2LK (FSE Chain)","Damage":"100","Startup":"5","Active":"3","Recovery":"8","Total":"15","Hit_Adv":"3","Block_Adv":"-1","Guard":"L","Cancel":"Chn Sp SA","Hitconfirm":"15 Sp\/Chn","Dmg_Scaling":"10% Starter","Punish_Adv":"7","PerfParry_Adv":"-9","DR_Cancel_onHit":"4","DR_Cancel_onBlock":"0","Hitstun":"14","Blockstun":"10","Hitstop":"9","DriveDmg_Block":"125","DriveDmg_Hit[PC]":"[500]","Drive_Gain":"62","SuperGain_Hit":"-","SuperGain_Block":"-","Invuln":"-","Armor":"-","Airborne":"-","Juggle_Start":"-","Juggle_Increase":"-","Juggle_Limit":"-","Notes":"Chained version during SA2 (FSE); 2f shorter special hitconfirm window when chained into; maintains juggle state vs. airborne opponents","Chip":null},{"input":"2MK","Damage":"500","Startup":"8","Active":"3","Recovery":"19","Total":"29","Hit_Adv":"1","Block_Adv":"-6","Guard":"L","Cancel":"Sp SA","Hitconfirm":"13","Dmg_Scaling":"20% Starter","Punish_Adv":"5","PerfParry_Adv":"-20","DR_Cancel_onHit":"11","DR_Cancel_onBlock":"4","Hitstun":"23","Blockstun":"16","Hitstop":"9","DriveDmg_Block":"2000","DriveDmg_Hit[PC]":"[4000]","Drive_Gain":"1000","SuperGain_Hit":"600 (420)","SuperGain_Block":"300 (150)","Invuln":"-","Armor":"-","Airborne":"-","Juggle_Start":"-","Juggle_Increase":"-","Juggle_Limit":"-","Notes":"Excellent range for a cancelable low poke in neutral; SA2 cancel: 15\/8; Range: 1.517 (1st frame: 1.446); DR cancel is delayed until after active frames","Chip":null},{"input":"2MK (FSE Chain)","Damage":"300","Startup":"8","Active":"3","Recovery":"19","Total":"29","Hit_Adv":"1","Block_Adv":"-6","Guard":"L","Cancel":"Chn Sp SA","Hitconfirm":"13 Sp \/ 15 Chn","Dmg_Scaling":"20% Starter","Punish_Adv":"5","PerfParry_Adv":"-20","DR_Cancel_onHit":"11","DR_Cancel_onBlock":"4","Hitstun":"23","Blockstun":"16","Hitstop":"8","DriveDmg_Block":"500","DriveDmg_Hit[PC]":"[1000]","Drive_Gain":"250","SuperGain_Hit":"-","SuperGain_Block":"-","Invuln":"-","Armor":"-","Airborne":"-","Juggle_Start":"-","Juggle_Increase":"-","Juggle_Limit":"-","Notes":"Chained version during SA2 (FSE); 1f shorter hitconfirm window when chained into; maintains juggle state vs. airborne opponents; Range: 1.517 (1st frame: 1.446); DR cancel is delayed until after active frames","Chip":null},{"input":"2HK","Damage":"900","Startup":"10","Active":"3","Recovery":"23","Total":"35","Hit_Adv":"HKD 32","Block_Adv":"-11","Guard":"L","Cancel":"-","Hitconfirm":"-","Dmg_Scaling":"-","Punish_Adv":"HKD 47","PerfParry_Adv":"-24","DR_Cancel_onHit":"-","DR_Cancel_onBlock":"-","Hitstun":"-","Blockstun":"15","Hitstop":"13","DriveDmg_Block":"4000","DriveDmg_Hit[PC]":"[10000]","Drive_Gain":"3000","SuperGain_Hit":"1000 (700)","SuperGain_Block":"500 (250)","Invuln":"-","Armor":"-","Airborne":"-","Juggle_Start":"-","Juggle_Increase":"1","Juggle_Limit":"0","Notes":"Not a Hard Knockdown when juggled into (requires free juggle state or Drive Rush 2HK); becomes fully cancelable during Feng Shui Engine (even when not chained into)","Chip":null},{"input":"2HK (FSE Chain)","Damage":"700","Startup":"10","Active":"3","Recovery":"23","Total":"35","Hit_Adv":"HKD 32","Block_Adv":"-11","Guard":"L","Cancel":"Sp SA","Hitconfirm":"17 Sp \/ 19 Chn","Dmg_Scaling":"-","Punish_Adv":"HKD 47","PerfParry_Adv":"-24","DR_Cancel_onHit":"HKD 48","DR_Cancel_onBlock":"5","Hitstun":"-","Blockstun":"15","Hitstop":"9","DriveDmg_Block":"1000","DriveDmg_Hit[PC]":"[2500]","Drive_Gain":"750","SuperGain_Hit":"-","SuperGain_Block":"-","Invuln":"-","Armor":"-","Airborne":"-","Juggle_Start":"-","Juggle_Increase":"-","Juggle_Limit":"-","Notes":"Chained version of 2HP during SA2 (FSE); maintains juggle state vs. airborne opponents; 4f shorter hitconfirm window when chained into","Chip":null},{"input":"j.LP","Damage":"300","Startup":"5","Active":"6","Recovery":"3 land","Total":"-","Hit_Adv":"-","Block_Adv":"-","Guard":"H","Cancel":"-","Hitconfirm":"-","Dmg_Scaling":"-","Punish_Adv":"-","PerfParry_Adv":"\u2264 -2","DR_Cancel_onHit":"-","DR_Cancel_onBlock":"-","Hitstun":"13","Blockstun":"9","Hitstop":"9","DriveDmg_Block":"1500","DriveDmg_Hit[PC]":"[2000]","Drive_Gain":"500","SuperGain_Hit":"300 (210)","SuperGain_Block":"150 (75)","Invuln":"-","Armor":"-","Airborne":"-","Juggle_Start":"-","Juggle_Increase":"-","Juggle_Limit":"-","Notes":"During FSE forward jump, can cancel into divekick","Chip":null},{"input":"j.LP (FSE Chain)","Damage":"100","Startup":"5","Active":"6","Recovery":"3 land","Total":"-","Hit_Adv":"KD","Block_Adv":"-","Guard":"H","Cancel":"Chn Sp","Hitconfirm":"-","Dmg_Scaling":"-","Punish_Adv":"KD","PerfParry_Adv":"-","DR_Cancel_onHit":"-","DR_Cancel_onBlock":"-","Hitstun":"13","Blockstun":"9","Hitstop":"9","DriveDmg_Block":"375","DriveDmg_Hit[PC]":"-","Drive_Gain":"125","SuperGain_Hit":"-","SuperGain_Block":"-","Invuln":"-","Armor":"-","Airborne":"-","Juggle_Start":"-","Juggle_Increase":"-","Juggle_Limit":"-","Notes":"Chained version during SA2 (FSE); maintains juggle state vs. airborne opponents","Chip":null},{"input":"j.MP","Damage":"700","Startup":"7","Active":"5","Recovery":"3 land","Total":"-","Hit_Adv":"-","Block_Adv":"-","Guard":"H","Cancel":"Sp","Hitconfirm":"-","Dmg_Scaling":"-","Punish_Adv":"-","PerfParry_Adv":"\u2264 -2","DR_Cancel_onHit":"-","DR_Cancel_onBlock":"-","Hitstun":"17","Blockstun":"11","Hitstop":"11","DriveDmg_Block":"2500","DriveDmg_Hit[PC]":"[4000]","Drive_Gain":"1000","SuperGain_Hit":"500 (350)","SuperGain_Block":"250 (125)","Invuln":"-","Armor":"-","Airborne":"-","Juggle_Start":"-","Juggle_Increase":"-","Juggle_Limit":"-","Notes":"Puts airborne opponents into limited juggle state; cancelable into divekick; instant j.MP > j.214KK is a useful option against corner throw loops (much less punishable than a blocked reversal); can only be used as a fuzzy instant overhead if the opponent is in Burnout and blocks a deep j.HK","Chip":null},{"input":"j.MP (FSE Chain)","Damage":"500","Startup":"7","Active":"5","Recovery":"3 land","Total":"-","Hit_Adv":"KD","Block_Adv":"-","Guard":"H","Cancel":"Chn Sp","Hitconfirm":"-","Dmg_Scaling":"-","Punish_Adv":"KD","PerfParry_Adv":"-","DR_Cancel_onHit":"-","DR_Cancel_onBlock":"-","Hitstun":"17","Blockstun":"11","Hitstop":"11","DriveDmg_Block":"-","DriveDmg_Hit[PC]":"-","Drive_Gain":"250","SuperGain_Hit":"-","SuperGain_Block":"-","Invuln":"-","Armor":"-","Airborne":"-","Juggle_Start":"-","Juggle_Increase":"-","Juggle_Limit":"-","Notes":"Chained version during SA2 (FSE); maintains juggle state vs. airborne opponents","Chip":null},{"input":"j.HP","Damage":"900","Startup":"12","Active":"6","Recovery":"3 land","Total":"-","Hit_Adv":"HKD 23(34)","Block_Adv":"-","Guard":"H","Cancel":"-","Hitconfirm":"-","Dmg_Scaling":"-","Punish_Adv":"HKD 23(34)","PerfParry_Adv":"\u2264 -2","DR_Cancel_onHit":"-","DR_Cancel_onBlock":"-","Hitstun":"-","Blockstun":"19","Hitstop":"13","DriveDmg_Block":"4000","DriveDmg_Hit[PC]":"[5000]","Drive_Gain":"2000","SuperGain_Hit":"1000 (700)","SuperGain_Block":"500 (250)","Invuln":"-","Armor":"-","Airborne":"-","Juggle_Start":"-","Juggle_Increase":"-","Juggle_Limit":"-","Notes":"Cross-up; causes a spike knockdown vs. airborne opponents with no Hard Knockdown; better KD Adv. when hitting lower to the ground; during FSE forward jump, can cancel into divekick","Chip":null},{"input":"j.HP (FSE Chain)","Damage":"700","Startup":"12","Active":"6","Recovery":"3 land","Total":"-","Hit_Adv":"KD","Block_Adv":"-","Guard":"H","Cancel":"Chn Sp","Hitconfirm":"-","Dmg_Scaling":"-","Punish_Adv":"KD","PerfParry_Adv":"-","DR_Cancel_onHit":"-","DR_Cancel_onBlock":"-","Hitstun":"-","Blockstun":"19","Hitstop":"13","DriveDmg_Block":"-","DriveDmg_Hit[PC]":"-","Drive_Gain":"500","SuperGain_Hit":"-","SuperGain_Block":"-","Invuln":"-","Armor":"-","Airborne":"-","Juggle_Start":"-","Juggle_Increase":"-","Juggle_Limit":"-","Notes":"Chained version during SA2 (FSE)","Chip":null},{"input":"j.LK","Damage":"300","Startup":"4","Active":"6","Recovery":"3 land","Total":"-","Hit_Adv":"-","Block_Adv":"-","Guard":"H","Cancel":"-","Hitconfirm":"-","Dmg_Scaling":"-","Punish_Adv":"-","PerfParry_Adv":"\u2264 -2","DR_Cancel_onHit":"-","DR_Cancel_onBlock":"-","Hitstun":"13","Blockstun":"9","Hitstop":"9","DriveDmg_Block":"1500","DriveDmg_Hit[PC]":"[2000]","Drive_Gain":"500","SuperGain_Hit":"300 (210)","SuperGain_Block":"150 (75)","Invuln":"-","Armor":"-","Airborne":"-","Juggle_Start":"-","Juggle_Increase":"-","Juggle_Limit":"-","Notes":"Cross-up; can be used as a fuzzy instant overhead; during FSE forward jump, can cancel into divekick","Chip":null},{"input":"j.LK (FSE Chain)","Damage":"100","Startup":"4","Active":"6","Recovery":"3 land","Total":"-","Hit_Adv":"KD","Block_Adv":"-","Guard":"H","Cancel":"Chn Sp","Hitconfirm":"-","Dmg_Scaling":"-","Punish_Adv":"KD","PerfParry_Adv":"-","DR_Cancel_onHit":"-","DR_Cancel_onBlock":"-","Hitstun":"13","Blockstun":"9","Hitstop":"9","DriveDmg_Block":"-","DriveDmg_Hit[PC]":"-","Drive_Gain":"125","SuperGain_Hit":"-","SuperGain_Block":"-","Invuln":"-","Armor":"-","Airborne":"-","Juggle_Start":"-","Juggle_Increase":"-","Juggle_Limit":"-","Notes":"Chained version during SA2 (FSE); maintains juggle state vs. airborne opponents","Chip":null},{"input":"j.MK","Damage":"500","Startup":"6","Active":"6","Recovery":"3 land","Total":"-","Hit_Adv":"-","Block_Adv":"-","Guard":"H","Cancel":"-","Hitconfirm":"-","Dmg_Scaling":"-","Punish_Adv":"-","PerfParry_Adv":"\u2264 -2","DR_Cancel_onHit":"-","DR_Cancel_onBlock":"-","Hitstun":"17","Blockstun":"13","Hitstop":"11","DriveDmg_Block":"2500","DriveDmg_Hit[PC]":"[4000]","Drive_Gain":"1000","SuperGain_Hit":"500 (350)","SuperGain_Block":"250 (125)","Invuln":"-","Armor":"-","Airborne":"-","Juggle_Start":"-","Juggle_Increase":"-","Juggle_Limit":"-","Notes":"Cross-up; during FSE forward jump, can cancel into divekick","Chip":null},{"input":"j.MK (FSE Chain)","Damage":"300","Startup":"6","Active":"6","Recovery":"3 land","Total":"-","Hit_Adv":"KD","Block_Adv":"-","Guard":"H","Cancel":"Chn Sp","Hitconfirm":"-","Dmg_Scaling":"-","Punish_Adv":"KD","PerfParry_Adv":"-","DR_Cancel_onHit":"-","DR_Cancel_onBlock":"-","Hitstun":"17","Blockstun":"13","Hitstop":"11","DriveDmg_Block":"625","DriveDmg_Hit[PC]":"[1000]","Drive_Gain":"250","SuperGain_Hit":"-","SuperGain_Block":"-","Invuln":"-","Armor":"-","Airborne":"-","Juggle_Start":"-","Juggle_Increase":"-","Juggle_Limit":"-","Notes":"Chained version during SA2 (FSE); maintains juggle state vs. airborne opponents","Chip":null},{"input":"7HK or 9HK","Damage":"800","Startup":"10","Active":"6","Recovery":"3 land","Total":"-","Hit_Adv":"-","Block_Adv":"-","Guard":"H","Cancel":"-","Hitconfirm":"-","Dmg_Scaling":"-","Punish_Adv":"-","PerfParry_Adv":"\u2264 -2","DR_Cancel_onHit":"-","DR_Cancel_onBlock":"-","Hitstun":"19","Blockstun":"15","Hitstop":"13","DriveDmg_Block":"4000","DriveDmg_Hit[PC]":"[5000]","Drive_Gain":"2000","SuperGain_Hit":"1000 (700)","SuperGain_Block":"500 (250)","Invuln":"-","Armor":"-","Airborne":"-","Juggle_Start":"-","Juggle_Increase":"-","Juggle_Limit":"-","Notes":"During FSE forward jump, can cancel into divekick; shifts Juri's hurtbox upward during startup","Chip":null},{"input":"j.HK (FSE Chain)","Damage":"600","Startup":"10","Active":"6","Recovery":"3 land","Total":"-","Hit_Adv":"KD","Block_Adv":"-","Guard":"H","Cancel":"Chn Sp","Hitconfirm":"-","Dmg_Scaling":"-","Punish_Adv":"KD","PerfParry_Adv":"-","DR_Cancel_onHit":"-","DR_Cancel_onBlock":"-","Hitstun":"19","Blockstun":"15","Hitstop":"13","DriveDmg_Block":"1000","DriveDmg_Hit[PC]":"-","Drive_Gain":"500","SuperGain_Hit":"-","SuperGain_Block":"-","Invuln":"-","Armor":"-","Airborne":"-","Juggle_Start":"-","Juggle_Increase":"-","Juggle_Limit":"-","Notes":"Chained version during SA2 (FSE); maintains juggle state vs. airborne opponents","Chip":null},{"input":"8HK","Damage":"800","Startup":"10","Active":"4","Recovery":"3 land","Total":"-","Hit_Adv":"-","Block_Adv":"-","Guard":"H","Cancel":"-","Hitconfirm":"-","Dmg_Scaling":"-","Punish_Adv":"-","PerfParry_Adv":"\u2264 -2","DR_Cancel_onHit":"-","DR_Cancel_onBlock":"-","Hitstun":"19","Blockstun":"15","Hitstop":"13","DriveDmg_Block":"4000","DriveDmg_Hit[PC]":"[5000]","Drive_Gain":"2000","SuperGain_Hit":"1000 (700)","SuperGain_Block":"500 (250)","Invuln":"-","Armor":"-","Airborne":"-","Juggle_Start":"-","Juggle_Increase":"-","Juggle_Limit":"-","Notes":"Hits on both sides (can cross-up if opponent tries to move underneath Juri); can be used as an air-to-air; when chained after FSE nj.MP, puts airborne opponents into juggle state; shifts Juri's hurtbox upward during startup","Chip":null},{"input":"8HK (FSE Chain)","Damage":"600","Startup":"10","Active":"4","Recovery":"3 land","Total":"-","Hit_Adv":"KD","Block_Adv":"-","Guard":"H","Cancel":"Chn Sp","Hitconfirm":"-","Dmg_Scaling":"-","Punish_Adv":"KD","PerfParry_Adv":"-","DR_Cancel_onHit":"-","DR_Cancel_onBlock":"-","Hitstun":"19","Blockstun":"15","Hitstop":"13","DriveDmg_Block":"-","DriveDmg_Hit[PC]":"-","Drive_Gain":"500","SuperGain_Hit":"-","SuperGain_Block":"-","Invuln":"-","Armor":"-","Airborne":"-","Juggle_Start":"-","Juggle_Increase":"-","Juggle_Limit":"-","Notes":"Chained version during SA2 (FSE); maintains juggle state vs. airborne opponents","Chip":null},{"input":"6MP","Damage":"600","Startup":"8","Active":"3","Recovery":"17","Total":"27","Hit_Adv":"4","Block_Adv":"-3","Guard":"LH","Cancel":"Sp SA","Hitconfirm":"15","Dmg_Scaling":"-","Punish_Adv":"8","PerfParry_Adv":"-18","DR_Cancel_onHit":"14","DR_Cancel_onBlock":"7","Hitstun":"24","Blockstun":"17","Hitstop":"11","DriveDmg_Block":"3000","DriveDmg_Hit[PC]":"[4000]","Drive_Gain":"1500","SuperGain_Hit":"500 (350)","SuperGain_Block":"250 (125)","Invuln":"-","Armor":"-","Airborne":"-","Juggle_Start":"-","Juggle_Increase":"-","Juggle_Limit":"-","Notes":"SA2 cancel: 16\/9","Chip":null},{"input":"6MP (FSE Chain)","Damage":"400","Startup":"8","Active":"3","Recovery":"17","Total":"27","Hit_Adv":"4","Block_Adv":"-3","Guard":"LH","Cancel":"Chn Sp SA","Hitconfirm":"15 Sp \/ 17 Chn","Dmg_Scaling":"-","Punish_Adv":"8","PerfParry_Adv":"-18","DR_Cancel_onHit":"14","DR_Cancel_onBlock":"7","Hitstun":"24","Blockstun":"17","Hitstop":"9","DriveDmg_Block":"750","DriveDmg_Hit[PC]":"[1000]","Drive_Gain":"375","SuperGain_Hit":"-","SuperGain_Block":"-","Invuln":"-","Armor":"-","Airborne":"-","Juggle_Start":"-","Juggle_Increase":"-","Juggle_Limit":"-","Notes":"Chained version during SA2 (FSE); 2f shorter hitconfirm window when chained into; maintains juggle state vs. airborne opponents","Chip":null},{"input":"6MK","Damage":"600","Startup":"21","Active":"2","Recovery":"21(23)","Total":"43(45)","Hit_Adv":"2","Block_Adv":"-3","Guard":"H","Cancel":"-","Hitconfirm":"-","Dmg_Scaling":"-","Punish_Adv":"6","PerfParry_Adv":"-21","DR_Cancel_onHit":"-","DR_Cancel_onBlock":"-","Hitstun":"25","Blockstun":"20","Hitstop":"11","DriveDmg_Block":"2500","DriveDmg_Hit[PC]":"[5000]","Drive_Gain":"1500","SuperGain_Hit":"700 (490)","SuperGain_Block":"350 (175)","Invuln":"-","Armor":"-","Airborne":"-","Juggle_Start":"-","Juggle_Increase":"-","Juggle_Limit":"-","Notes":"Not airborne despite the animation; 2 extra recovery frames on whiff","Chip":null},{"input":"6MK (FSE Chain)","Damage":"400","Startup":"21","Active":"2","Recovery":"21(23)","Total":"43(45)","Hit_Adv":"KD 25","Block_Adv":"-3","Guard":"H","Cancel":"Sp SA","Hitconfirm":"14 Sp\/Chn","Dmg_Scaling":"-","Punish_Adv":"KD 25","PerfParry_Adv":"-21","DR_Cancel_onHit":"KD 37","DR_Cancel_onBlock":"9","Hitstun":"-","Blockstun":"20","Hitstop":"9","DriveDmg_Block":"625","DriveDmg_Hit[PC]":"[1250]","Drive_Gain":"375","SuperGain_Hit":"-","SuperGain_Block":"-","Invuln":"-","Armor":"-","Airborne":"-","Juggle_Start":"-","Juggle_Increase":"-","Juggle_Limit":"-","Notes":"Chained Feng Shui Engine version; not airborne despite the animation; the special\/chain cancel window only applies when chaining into 6MK and the KD doesn't allow anything to juggle on hit; 2 extra recovery frames on whiff; special\/DR cancel is delayed until after 2nd active frame","Chip":null},{"input":"6HP","Damage":"500x2","Startup":"15(23)","Active":"3(5)3","Recovery":"20","Total":"45","Hit_Adv":"2","Block_Adv":"-4","Guard":"LH","Cancel":"Sp SA","Hitconfirm":"27\/14","Dmg_Scaling":"-","Punish_Adv":"6","PerfParry_Adv":"-21","DR_Cancel_onHit":"16 \/ 15","DR_Cancel_onBlock":"6 \/ 9","Hitstun":"26,25","Blockstun":"16,19","Hitstop":"5,10","DriveDmg_Block":"2500x2","DriveDmg_Hit[PC]":"[5000x2]","Drive_Gain":"1250x2","SuperGain_Hit":"500x2 (350x2)","SuperGain_Block":"250x2 (125x2)","Invuln":"-","Armor":"-","Airborne":"-","Juggle_Start":"1","Juggle_Increase":"1,1","Juggle_Limit":"0,1","Notes":"Both hits are cancelable; 23f startup for 2nd hit only; 1st hit has more hitstun and blockstun for cancels; both hits put airborne opponent into limited juggle state; carries counter-hit\/Punish Counter advantage through both hits; SA2 cancel: 18\/8 (1st hit), 17\/11 (2nd hit)","Chip":null},{"input":"6HP (FSE Chain)","Damage":"400x2","Startup":"15(23)","Active":"3(5)3","Recovery":"20","Total":"45","Hit_Adv":"KD 40","Block_Adv":"-4","Guard":"LH","Cancel":"Chn Sp SA","Hitconfirm":"27(14) Sp \/ 29(16) Chn","Dmg_Scaling":"-","Punish_Adv":"KD 40","PerfParry_Adv":"-21","DR_Cancel_onHit":"KD 48\/53","DR_Cancel_onBlock":"6 \/ 9","Hitstun":"-","Blockstun":"16,19","Hitstop":"5,6","DriveDmg_Block":"625x2","DriveDmg_Hit[PC]":"[1250x2]","Drive_Gain":"313,312","SuperGain_Hit":"-","SuperGain_Block":"-","Invuln":"-","Armor":"-","Airborne":"-","Juggle_Start":"-","Juggle_Increase":"-","Juggle_Limit":"-","Notes":"Chained version during SA2 (FSE); maintains juggle state vs. airborne opponents; 4f shorter hitconfirm window when chained into","Chip":null},{"input":"4HK","Damage":"400x2","Startup":"10(19)","Active":"3(6)3","Recovery":"19","Total":"40","Hit_Adv":"-2","Block_Adv":"-6","Guard":"LH","Cancel":"Sp SA","Hitconfirm":"39\/17","Dmg_Scaling":"-","Punish_Adv":"2","PerfParry_Adv":"-20","DR_Cancel_onHit":"10","DR_Cancel_onBlock":"4 \/ 6","Hitstun":"20,20","Blockstun":"14,16","Hitstop":"13,13","DriveDmg_Block":"1500x2","DriveDmg_Hit[PC]":"[4000x2]","Drive_Gain":"750x2","SuperGain_Hit":"500x2 (350x2)","SuperGain_Block":"250x2 (125x2)","Invuln":"-","Armor":"-","Airborne":"-","Juggle_Start":"-","Juggle_Increase":"-","Juggle_Limit":"-","Notes":"Both hits are cancelable; 1st hit forces stand and puts airborne opponents into limited juggle state; 2nd hit causes spike knockdown vs. airborne opponents; 19f startup for 2nd hit only; carries counter-hit\/Punish Counter advantage through both hits; SA2 cancel: 12\/6 (1st hit), 12\/8 (2nd hit)","Chip":null},{"input":"4HK (FSE Chain)","Damage":"300x2","Startup":"10(19)","Active":"3(6)3","Recovery":"19","Total":"40","Hit_Adv":"KD 20","Block_Adv":"-6","Guard":"LH","Cancel":"Chn Sp SA","Hitconfirm":"39(17) Sp \/ 41(19) Chn","Dmg_Scaling":"-","Punish_Adv":"KD 20","PerfParry_Adv":"-20","DR_Cancel_onHit":"KD 51\/32","DR_Cancel_onBlock":"4 \/ 6","Hitstun":"-","Blockstun":"14,16","Hitstop":"9,9","DriveDmg_Block":"375x2","DriveDmg_Hit[PC]":"[1000x2]","Drive_Gain":"188,187","SuperGain_Hit":"-","SuperGain_Block":"-","Invuln":"-","Armor":"-","Airborne":"-","Juggle_Start":"-","Juggle_Increase":"-","Juggle_Limit":"-","Notes":"Chained version during SA2 (FSE); both hits knock down; 8f shorter hitconfirm window when chained into","Chip":null},{"input":"5MP~4HP","Damage":"500","Startup":"12","Active":"3","Recovery":"19","Total":"33","Hit_Adv":"KD 35","Block_Adv":"-3","Guard":"LH","Cancel":"TC","Hitconfirm":"45","Dmg_Scaling":"-","Punish_Adv":"KD 35","PerfParry_Adv":"-","DR_Cancel_onHit":"-","DR_Cancel_onBlock":"-","Hitstun":"-","Blockstun":"19","Hitstop":"10","DriveDmg_Block":"2000","DriveDmg_Hit[PC]":"-","Drive_Gain":"1000","SuperGain_Hit":"1000 (700)","SuperGain_Block":"500 (250)","Invuln":"-","Armor":"-","Airborne":"-","Juggle_Start":"-","Juggle_Increase":"-","Juggle_Limit":"-","Notes":"Safe Target Combo starter that leaves ample time to confirm the final hit; 4HP cannot be delayed to create a blockstring gap","Chip":null},{"input":"5MP~4HP~HP","Damage":"600(480)","Startup":"17","Active":"3","Recovery":"27","Total":"46","Hit_Adv":"KD 32","Block_Adv":"-16","Guard":"LH","Cancel":"-","Hitconfirm":"-","Dmg_Scaling":"-","Punish_Adv":"-","PerfParry_Adv":"-28","DR_Cancel_onHit":"-","DR_Cancel_onBlock":"-","Hitstun":"-","Blockstun":"14","Hitstop":"13","DriveDmg_Block":null,"DriveDmg_Hit[PC]":null,"Drive_Gain":null,"SuperGain_Hit":null,"SuperGain_Block":null,"Invuln":"-","Armor":"-","Airborne":"-","Juggle_Start":"-","Juggle_Increase":"-","Juggle_Limit":"-","Notes":null,"Chip":null},{"input":"5MP~4HP~HP","Damage":null,"Startup":null,"Active":null,"Recovery":null,"Total":null,"Hit_Adv":null,"Block_Adv":null,"Guard":null,"Cancel":null,"Hitconfirm":null,"Dmg_Scaling":null,"Punish_Adv":null,"PerfParry_Adv":null,"DR_Cancel_onHit":null,"DR_Cancel_onBlock":null,"Hitstun":null,"Blockstun":null,"Hitstop":null,"DriveDmg_Block":"1000","DriveDmg_Hit[PC]":"-","Drive_Gain":"1000","SuperGain_Hit":"500 (350)","SuperGain_Block":"250 (125)","Invuln":null,"Armor":null,"Airborne":null,"Juggle_Start":null,"Juggle_Increase":null,"Juggle_Limit":null,"Notes":"(refers to scaled damage); not airborne despite the animation; if HP is delayed to final possible frame, creates a 1f blockstring gap from 4HP","Chip":null},{"input":"LPLK","Damage":"1200 (2040)","Startup":"5","Active":"3","Recovery":"23","Total":"30","Hit_Adv":"KD 25","Block_Adv":"-","Guard":"T","Cancel":null,"Hitconfirm":null,"Dmg_Scaling":"20% Immediate","Punish_Adv":"HKD 25","PerfParry_Adv":"-","DR_Cancel_onHit":null,"DR_Cancel_onBlock":null,"Hitstun":null,"Blockstun":"-","Hitstop":"-","DriveDmg_Block":"-","DriveDmg_Hit[PC]":"[10000]","Drive_Gain":"2000","SuperGain_Hit":"2000(1400) [4000(2800)]","SuperGain_Block":null,"Invuln":"-","Armor":"-","Airborne":null,"Juggle_Start":"-","Juggle_Increase":"-","Juggle_Limit":"-","Notes":"Has access to corner throw loops by dashing (3)","Chip":"-"},{"input":"4LPLK","Damage":"1200 (2040)","Startup":"5","Active":"3","Recovery":"23","Total":"30","Hit_Adv":"KD 18","Block_Adv":"-","Guard":"T","Cancel":null,"Hitconfirm":null,"Dmg_Scaling":"20% Immediate","Punish_Adv":"HKD 18","PerfParry_Adv":"-","DR_Cancel_onHit":null,"DR_Cancel_onBlock":null,"Hitstun":null,"Blockstun":"-","Hitstop":"-","DriveDmg_Block":"-","DriveDmg_Hit[PC]":"[10000]","Drive_Gain":"2000","SuperGain_Hit":"2000(1400) [4000(2800)]","SuperGain_Block":null,"Invuln":"-","Armor":"-","Airborne":null,"Juggle_Start":"-","Juggle_Increase":"-","Juggle_Limit":"-","Notes":"No throw oki after back throwing opponent into corner, but can use meaty strikes","Chip":"-"},{"input":"j.LPLK","Damage":"1200 (2040)","Startup":"5","Active":"3","Recovery":"3 land","Total":"-","Hit_Adv":"KD 2(4)","Block_Adv":"-","Guard":"T","Cancel":null,"Hitconfirm":null,"Dmg_Scaling":"-","Punish_Adv":"HKD 2(4)","PerfParry_Adv":"-","DR_Cancel_onHit":null,"DR_Cancel_onBlock":null,"Hitstun":null,"Blockstun":"-","Hitstop":"-","DriveDmg_Block":"-","DriveDmg_Hit[PC]":"[10000]","Drive_Gain":"2000","SuperGain_Hit":"2000(1400) [4000(2800)]","SuperGain_Block":null,"Invuln":"-","Armor":"-","Airborne":null,"Juggle_Start":"-","Juggle_Increase":"-","Juggle_Limit":"-","Notes":"KD Adv. varies based on height (lower height = worse advantage); switches sides; no oki after throwing opponent back into the corner","Chip":"-"},{"input":"HPHK","Damage":"800","Startup":"26","Active":"2","Recovery":"35","Total":"62","Hit_Adv":"KD 35 \/ Wall Splat KD 65","Block_Adv":"-3 \/ Wall Splat HKD 72","Guard":"LH","Cancel":null,"Hitconfirm":null,"Dmg_Scaling":"20% Starter","Punish_Adv":"Crumple (Standing 21, Juggle 46, HKD 104)","PerfParry_Adv":"-35","DR_Cancel_onHit":null,"DR_Cancel_onBlock":null,"Hitstun":null,"Blockstun":"34","Hitstop":"25","DriveDmg_Block":"5000","DriveDmg_Hit[PC]":"10000 [15000]","Drive_Gain":"-10000","SuperGain_Hit":"[3000(2100)]","SuperGain_Block":null,"Invuln":"-","Armor":"1-27","Airborne":null,"Juggle_Start":"0","Juggle_Increase":"1","Juggle_Limit":"0","Notes":"See Drive Impact. Airborne connect gives spinning juggle state on Punish Counter or corner Wall Splat with variable height.","Chip":"200"},{"input":"6HPHK","Damage":"500 recoverable","Startup":"20","Active":"3","Recovery":"26(31)","Total":"48(53)","Hit_Adv":"KD 23","Block_Adv":"-8","Guard":"LH","Cancel":null,"Hitconfirm":null,"Dmg_Scaling":"-","Punish_Adv":"KD 23","PerfParry_Adv":"-27","DR_Cancel_onHit":null,"DR_Cancel_onBlock":null,"Hitstun":null,"Blockstun":"21","Hitstop":"20","DriveDmg_Block":"-","DriveDmg_Hit[PC]":"-","Drive_Gain":"-20000","SuperGain_Hit":"-","SuperGain_Block":null,"Invuln":"1-22 Full","Armor":"Break","Airborne":null,"Juggle_Start":"200","Juggle_Increase":"100","Juggle_Limit":"1","Notes":"5f extra recovery on hit; see Drive Reversal.","Chip":"125 recoverable"},{"input":"MPMK","Damage":"-","Startup":"1","Active":"8 or until released","Recovery":"29(1)(11)","Total":"37(3)","Hit_Adv":"-","Block_Adv":"-","Guard":"-","Cancel":null,"Hitconfirm":null,"Dmg_Scaling":"50% Multiplier (Perfect)","Punish_Adv":"-","PerfParry_Adv":"-","DR_Cancel_onHit":null,"DR_Cancel_onBlock":null,"Hitstun":null,"Blockstun":"-","Hitstop":"-","DriveDmg_Block":"-","DriveDmg_Hit[PC]":"-","Drive_Gain":"-5000,250~","SuperGain_Hit":"-","SuperGain_Block":null,"Invuln":"6 Full (after Perfect Parry)","Armor":"-","Airborne":null,"Juggle_Start":"-","Juggle_Increase":"-","Juggle_Limit":"-","Notes":"See Drive Parry. Perfect Parrying has only 1F of recovery and disables the opponent from canceling their attack. Perfect Parrying projectiles puts you into fixed 11 frames of recovery.","Chip":"-"},{"input":"66","Damage":"-","Startup":"9(11)","Active":"45(46)","Recovery":"24(23)","Total":"-","Hit_Adv":"-","Block_Adv":"-","Guard":"-","Cancel":null,"Hitconfirm":null,"Dmg_Scaling":"15% Multiplier (Mid-Combo)","Punish_Adv":"-","PerfParry_Adv":"-","DR_Cancel_onHit":null,"DR_Cancel_onBlock":null,"Hitstun":null,"Blockstun":"-","Hitstop":"-","DriveDmg_Block":null,"DriveDmg_Hit[PC]":null,"Drive_Gain":null,"SuperGain_Hit":null,"SuperGain_Block":null,"Invuln":"-","Armor":"-","Airborne":null,"Juggle_Start":"-","Juggle_Increase":"-","Juggle_Limit":"-","Notes":null,"Chip":"-"},{"input":"66","Damage":null,"Startup":null,"Active":null,"Recovery":null,"Total":null,"Hit_Adv":null,"Block_Adv":null,"Guard":null,"Cancel":null,"Hitconfirm":null,"Dmg_Scaling":null,"Punish_Adv":null,"PerfParry_Adv":null,"DR_Cancel_onHit":null,"DR_Cancel_onBlock":null,"Hitstun":null,"Blockstun":null,"Hitstop":null,"DriveDmg_Block":"-","DriveDmg_Hit[PC]":"-","Drive_Gain":"-10000(-30000)","SuperGain_Hit":"-","SuperGain_Block":null,"Invuln":null,"Armor":null,"Airborne":null,"Juggle_Start":null,"Juggle_Increase":null,"Juggle_Limit":null,"Notes":"See Drive Rush. Frame data shown in parentheses refers to the Drive Rush version used from a Parry. Distance: 0.641 (min\/throw), 2.479 (min\/block), 3.999 (max\/final DR frame)","Chip":null},{"input":"214LK","Damage":"600","Startup":"10","Active":"4","Recovery":"19(21)","Total":"32(34)","Hit_Adv":"KD 37","Block_Adv":"-4","Guard":"LH","Cancel":"SA3","Hitconfirm":"19","Dmg_Scaling":"-","Punish_Adv":"KD 37","PerfParry_Adv":"-21","DR_Cancel_onHit":null,"DR_Cancel_onBlock":null,"Hitstun":null,"Blockstun":"21","Hitstop":"9(11)","DriveDmg_Block":"2500","DriveDmg_Hit[PC]":"[5000]","Drive_Gain":"2000","SuperGain_Hit":"600 (420)","SuperGain_Block":"300 (150)","Invuln":"-","Armor":"-","Airborne":"-","Juggle_Start":"-","Juggle_Increase":"-","Juggle_Limit":"-","Notes":"Gains 1 Fuha stock on hit\/block\/whiff on frame 10; 1-hit projectile clash hitbox on frames 8-13; puts opponent into limited juggle state (only combos into SA3); does not move forward during startup; 2f extra recovery on whiff","Chip":"150"},{"input":"214MK","Damage":"600","Startup":"13","Active":"4","Recovery":"21","Total":"37","Hit_Adv":"KD 37","Block_Adv":"-6","Guard":"LH","Cancel":"SA3","Hitconfirm":"24","Dmg_Scaling":"-","Punish_Adv":"KD 37","PerfParry_Adv":"-23","DR_Cancel_onHit":null,"DR_Cancel_onBlock":null,"Hitstun":null,"Blockstun":"19","Hitstop":"9(11)","DriveDmg_Block":"2500","DriveDmg_Hit[PC]":"[5000]","Drive_Gain":"2000","SuperGain_Hit":"600 (420)","SuperGain_Block":"300 (150)","Invuln":"-","Armor":"-","Airborne":"-","Juggle_Start":"-","Juggle_Increase":"-","Juggle_Limit":"-","Notes":"Gains 1 Fuha stock on hit\/block\/whiff on frame 13; 1-hit projectile clash hitbox on frames 11-16; puts opponent into limited juggle state (only combos into SA3); takes small step forward, making it more consistent in combos (but does not combo naturally from 5LK)","Chip":"150"},{"input":"214HK","Damage":"500","Startup":"25","Active":"4","Recovery":"20(22)","Total":"48(50)","Hit_Adv":"KD 46","Block_Adv":"-8","Guard":"LH","Cancel":"SA3","Hitconfirm":"16","Dmg_Scaling":"-","Punish_Adv":"KD 46","PerfParry_Adv":"-24","DR_Cancel_onHit":null,"DR_Cancel_onBlock":null,"Hitstun":null,"Blockstun":"15","Hitstop":"11","DriveDmg_Block":"2500","DriveDmg_Hit[PC]":"[5000]","Drive_Gain":"2000","SuperGain_Hit":"600 (420)","SuperGain_Block":"300 (150)","Invuln":"-","Armor":"-","Airborne":"-","Juggle_Start":"-","Juggle_Increase":"-","Juggle_Limit":"-","Notes":"Gains 1 Fuha stock on hit\/block\/whiff on frame 25; 1-hit projectile clash hitbox on frames 23-28; launches opponent high into a limited juggle state; takes large step forward (but only combos naturally from 5HP, 2HP, and first hit of 5MK and 6HP); 2f extra recovery on block","Chip":"125"},{"input":"214KK","Damage":"600","Startup":"16","Active":"4","Recovery":"23","Total":"42","Hit_Adv":"KD 45","Block_Adv":"-12","Guard":"LH","Cancel":"SA2 SA3","Hitconfirm":"28","Dmg_Scaling":"-","Punish_Adv":"KD 45","PerfParry_Adv":"-25","DR_Cancel_onHit":null,"DR_Cancel_onBlock":null,"Hitstun":null,"Blockstun":"15","Hitstop":"11","DriveDmg_Block":"2500","DriveDmg_Hit[PC]":"[5000]","Drive_Gain":"-20000","SuperGain_Hit":"600 (420)","SuperGain_Block":"300 (150)","Invuln":"-","Armor":"-","Airborne":"-","Juggle_Start":"-","Juggle_Increase":"-","Juggle_Limit":"-","Notes":"Gains 1 Fuha stock on hit\/block\/whiff on frame 16; 2-hit OD projectile clash hitbox on frames 14-19; launches opponent high into a limited juggle state; takes small step forward (consistent like the MK version, but does not combo naturally from light normals); SA2 cancel: KD51\/-6","Chip":"150"},{"input":"236LK","Damage":"400","Startup":"16","Active":"10","Recovery":"20","Total":"45","Hit_Adv":"-2","Block_Adv":"-8","Guard":"LH","Cancel":"SA3","Hitconfirm":"3","Dmg_Scaling":"-","Punish_Adv":"2","PerfParry_Adv":"-19","DR_Cancel_onHit":null,"DR_Cancel_onBlock":null,"Hitstun":null,"Blockstun":"22","Hitstop":"8","DriveDmg_Block":"2500","DriveDmg_Hit[PC]":"[3000]","Drive_Gain":"1000","SuperGain_Hit":"600 (420)","SuperGain_Block":"300 (150)","Invuln":"-","Armor":"-","Airborne":"-","Juggle_Start":"-","Juggle_Increase":"-","Juggle_Limit":"-","Notes":"1-hit projectile hitbox (can lose to projectile-invuln moves); very short range","Chip":"100"},{"input":"236LK (1 Stock)","Damage":"600","Startup":"16","Active":"[80]","Recovery":"29","Total":"45","Hit_Adv":"1","Block_Adv":"-3","Guard":"LH","Cancel":"SA3","Hitconfirm":"3 (SA\/follow-up)","Dmg_Scaling":"20% Starter; Combo (2 hits)","Punish_Adv":"5","PerfParry_Adv":"-19","DR_Cancel_onHit":null,"DR_Cancel_onBlock":null,"Hitstun":null,"Blockstun":"27","Hitstop":"8","DriveDmg_Block":"2500","DriveDmg_Hit[PC]":"[3000]","Drive_Gain":"1000","SuperGain_Hit":"600 (420)","SuperGain_Block":"300 (150)","Invuln":"-","Armor":"-","Airborne":"-","Juggle_Start":"-","Juggle_Increase":"-","Juggle_Limit":"-","Notes":"1-hit projectile; costs 1 Fuha stock; can press MK or HK to cancel into other 236K specials for 1 Fuha stock (within the first 3 active frames)","Chip":"150"},{"input":"236LKMK","Damage":"400x2","Startup":"11","Active":"[120]","Recovery":"27","Total":"38","Hit_Adv":"KD 39","Block_Adv":"-2","Guard":"LH","Cancel":"SA2 SA3","Hitconfirm":"7 SA \/ 4 follow-up","Dmg_Scaling":"-","Punish_Adv":"KD 42","PerfParry_Adv":"-6","DR_Cancel_onHit":null,"DR_Cancel_onBlock":null,"Hitstun":null,"Blockstun":"26 total","Hitstop":"5,6","DriveDmg_Block":"1500x2","DriveDmg_Hit[PC]":"[2500x2]","Drive_Gain":"-20000","SuperGain_Hit":"300x2 (210x2)","SuperGain_Block":"150x2 (75x2)","Invuln":"-","Armor":"-","Airborne":"-","Juggle_Start":"-","Juggle_Increase":"-","Juggle_Limit":"-","Notes":"2-hit OD projectile; only the 2nd hit knocks down; can press MK or HK to cancel into other OD 236K specials for 1 Fuha stock and 1 Drive bar; SA2 cancel: KD57\/17","Chip":"100x2"},{"input":"236MK","Damage":"600","Startup":"24","Active":"4","Recovery":"19 land","Total":"46","Hit_Adv":"3 (KD 21~23)","Block_Adv":"-10","Guard":"LH","Cancel":"SA3","Hitconfirm":"23","Dmg_Scaling":"-","Punish_Adv":"7","PerfParry_Adv":"-21","DR_Cancel_onHit":null,"DR_Cancel_onBlock":null,"Hitstun":null,"Blockstun":"13","Hitstop":"13","DriveDmg_Block":"3000","DriveDmg_Hit[PC]":"[5000]","Drive_Gain":"2000","SuperGain_Hit":"800 (560)","SuperGain_Block":"400 (200)","Invuln":"-","Armor":"-","Airborne":"8-27 (FKD)","Juggle_Start":"-","Juggle_Increase":"-","Juggle_Limit":"-","Notes":"8-27f low crush; KD vs. airborne opponents","Chip":"150"},{"input":"236MK (1 Stock)","Damage":"600","Startup":"24","Active":"4","Recovery":"19 land","Total":"46","Hit_Adv":"8 (KD 21~23)","Block_Adv":"-10","Guard":"LH","Cancel":"SA3","Hitconfirm":"23 (SA\/follow-up)","Dmg_Scaling":"20% Starter; Combo (2 hits)","Punish_Adv":"12","PerfParry_Adv":"-21","DR_Cancel_onHit":null,"DR_Cancel_onBlock":null,"Hitstun":null,"Blockstun":"13","Hitstop":"13","DriveDmg_Block":"3000","DriveDmg_Hit[PC]":"[5000]","Drive_Gain":"2000","SuperGain_Hit":"800 (560)","SuperGain_Block":"400 (200)","Invuln":"-","Armor":"-","Airborne":"8-27 (FKD)","Juggle_Start":"-","Juggle_Increase":"-","Juggle_Limit":"-","Notes":"Costs 1 Fuha stock; 8-27f low crush; KD vs. airborne opponents; can press LK or HK to cancel into other 236K specials for 1 Fuha stock","Chip":"150"},{"input":"236LKHK","Damage":"800","Startup":"24","Active":"4","Recovery":"19 land","Total":"46","Hit_Adv":"9 (KD 56~57)","Block_Adv":"-10","Guard":"LH","Cancel":"SA2 SA3","Hitconfirm":"23 (SA\/follow-up)","Dmg_Scaling":"20% Starter; Combo (2 hits)","Punish_Adv":"13","PerfParry_Adv":"-21","DR_Cancel_onHit":null,"DR_Cancel_onBlock":null,"Hitstun":null,"Blockstun":"13","Hitstop":"13","DriveDmg_Block":"3000","DriveDmg_Hit[PC]":"[5000]","Drive_Gain":"-20000","SuperGain_Hit":"800 (560)","SuperGain_Block":"400 (200)","Invuln":"-","Armor":"-","Airborne":"8-27 (FKD)","Juggle_Start":"-","Juggle_Increase":"-","Juggle_Limit":"-","Notes":"8-27f low crush; OTG bounce vs. airborne opponents (limited juggle state); pressing LK or HK cancels to other OD 236K specials for 1 Fuha stock  1 Drive bar; SA2 cancel: 16\/-3","Chip":"200"},{"input":"236HK","Damage":"700,500 (1200)","Startup":"18","Active":"4(12)3","Recovery":"27","Total":"63","Hit_Adv":"KD 37","Block_Adv":"-12","Guard":"LH","Cancel":"SA3","Hitconfirm":"36 (SA\/follow-up)","Dmg_Scaling":"-","Punish_Adv":"KD 27","PerfParry_Adv":"-29","DR_Cancel_onHit":null,"DR_Cancel_onBlock":null,"Hitstun":null,"Blockstun":"20","Hitstop":"12(14)","DriveDmg_Block":"4000","DriveDmg_Hit[PC]":"[5000]","Drive_Gain":"1000","SuperGain_Hit":"700 (490)","SuperGain_Block":"350 (175)","Invuln":"-","Armor":"-","Airborne":"-","Juggle_Start":"-","Juggle_Increase":"-","Juggle_Limit":"-","Notes":"Puts airborne opponents into limited juggle state (only high airborne connect launches high enough for follow-up juggle besides SA3 cancel); good juggle ender for damage when canceling to SA3","Chip":"250"},{"input":"236MKHK","Damage":"400x3 (1200)","Startup":"18","Active":"4(12)3(28)5","Recovery":"28","Total":"97","Hit_Adv":"KD 32","Block_Adv":"-16","Guard":"LH","Cancel":"SA2 SA3","Hitconfirm":"77(38) (SA\/follow-up)","Dmg_Scaling":"20% Starter","Punish_Adv":"KD 32","PerfParry_Adv":"-31","DR_Cancel_onHit":null,"DR_Cancel_onBlock":null,"Hitstun":null,"Blockstun":"64 total","Hitstop":"4,5,12 (6,7,14)","DriveDmg_Block":"2000x3","DriveDmg_Hit[PC]":"[1700x2,1600]","Drive_Gain":"-20000","SuperGain_Hit":"300x2,200 (210x2,140)","SuperGain_Block":"150x2,100 (75x2,50)","Invuln":"-","Armor":"-","Airborne":"-","Juggle_Start":"-","Juggle_Increase":"-","Juggle_Limit":"-","Notes":"All 3 hits are Super cancelable; first hit keeps opponent grounded, 2nd and 3rd hits put opponent into limited juggle state; can press LK or MK to cancel any hit into other OD 236K specials for 1 Fuha stock and 1 Drive bar; SA2 cancel: 17\/17 (1st hit), KD54\/15 (2nd hit), KD52\/4 (3rd hit); 3rd hit cannot juggle into held SA2 dash attack","Chip":"100x3 (300)"},{"input":"623LP","Damage":"400x2","Startup":"11","Active":"3(2)2","Recovery":"22","Total":"39","Hit_Adv":"KD 37","Block_Adv":"-8","Guard":"LH","Cancel":"SA3","Hitconfirm":"17","Dmg_Scaling":"-","Punish_Adv":"KD 37","PerfParry_Adv":"-27(-22)","DR_Cancel_onHit":null,"DR_Cancel_onBlock":null,"Hitstun":null,"Blockstun":"21 total","Hitstop":"3,6","DriveDmg_Block":"2000x2","DriveDmg_Hit[PC]":"[2500x2]","Drive_Gain":"1000x2","SuperGain_Hit":"500x2 (350x2)","SuperGain_Block":"250x2 (125x2)","Invuln":"-","Armor":"-","Airborne":"-","Juggle_Start":"-","Juggle_Increase":"-","Juggle_Limit":"-","Notes":"Both hits are SA3 cancelable; not airborne; fairly consistent combo ender","Chip":"100x2"},{"input":"623MP","Damage":"300x4 (1200)","Startup":"5","Active":"8(5)2(3)2","Recovery":"2414 land","Total":"62","Hit_Adv":"KD 31","Block_Adv":"-37","Guard":"LH","Cancel":"-","Hitconfirm":"-","Dmg_Scaling":"-","Punish_Adv":"KD 31","PerfParry_Adv":"-49(-56)","DR_Cancel_onHit":null,"DR_Cancel_onBlock":null,"Hitstun":null,"Blockstun":"21 total","Hitstop":"4,3,3,13","DriveDmg_Block":"2000x2","DriveDmg_Hit[PC]":"[5000]","Drive_Gain":"500x4 (500x2)","SuperGain_Hit":"300x2,200x2 (210x2,140x2)","SuperGain_Block":"150x2 (75x2)","Invuln":"1-8 Air","Armor":"-","Airborne":"9-48 (FKD)","Juggle_Start":"-","Juggle_Increase":"-","Juggle_Limit":"-","Notes":"Strong anti-air but cannot hit cross-up; slightly less horizontal range than 623HP","Chip":"75x2 (150)"},{"input":"623HP","Damage":"300x4 (1200)","Startup":"5","Active":"8(5)2(3)2","Recovery":"2414 land","Total":"62","Hit_Adv":"KD 28","Block_Adv":"-37(-41)","Guard":"LH","Cancel":"-","Hitconfirm":"-","Dmg_Scaling":"-","Punish_Adv":"KD 28","PerfParry_Adv":"-49(-56)","DR_Cancel_onHit":null,"DR_Cancel_onBlock":null,"Hitstun":null,"Blockstun":"21 total (17 crouch)","Hitstop":"4,3,3,13","DriveDmg_Block":"2000x2","DriveDmg_Hit[PC]":"[5000]","Drive_Gain":"500x4 (500x2)","SuperGain_Hit":"300x2,200x2 (210x2,140x2)","SuperGain_Block":"150x2 (75x2)","Invuln":"1-8 Air","Armor":"-","Airborne":"7-48 (FKD)","Juggle_Start":"-","Juggle_Increase":"-","Juggle_Limit":"-","Notes":"Only 1 hit connects vs. crouch block (4f worse oB, less chip damage); strong combo ender and anti-air but cannot hit cross-up; slightly more horizontal range than 623MP","Chip":"75,(75)"},{"input":"623PP","Damage":"600,200x3,400 (1600)","Startup":"6","Active":"4(1)2(6)2(2)2","Recovery":"3219 land","Total":"75","Hit_Adv":"KD 5","Block_Adv":"-48","Guard":"LH","Cancel":"-","Hitconfirm":"-","Dmg_Scaling":"-","Punish_Adv":"KD 5","PerfParry_Adv":"-68","DR_Cancel_onHit":null,"DR_Cancel_onBlock":null,"Hitstun":null,"Blockstun":"22 total","Hitstop":"3x4,8","DriveDmg_Block":"2000x2","DriveDmg_Hit[PC]":"-","Drive_Gain":"-20000","SuperGain_Hit":"400,100x3,200 (280,70x3,140)","SuperGain_Block":"200,50 (100,25)","Invuln":"1-9 Full","Armor":"-","Airborne":"10-56 (FKD)","Juggle_Start":"-","Juggle_Increase":"-","Juggle_Limit":"-","Notes":"Juri's primary reversal option; final attack comes out on hit only; cannot hit cross-up","Chip":"150,50 (200)"},{"input":"j.214K","Damage":"400","Startup":"18","Active":"until landing","Recovery":"18 land","Total":"-","Hit_Adv":"KD 34(41)","Block_Adv":"-10(-3)","Guard":"LH","Cancel":"-","Hitconfirm":"-","Dmg_Scaling":"-","Punish_Adv":"KD 34(41)","PerfParry_Adv":"-24(-17)","DR_Cancel_onHit":null,"DR_Cancel_onBlock":null,"Hitstun":null,"Blockstun":"16","Hitstop":"5","DriveDmg_Block":"3000","DriveDmg_Hit[PC]":"[5000]","Drive_Gain":"2000","SuperGain_Hit":"600 (420)","SuperGain_Block":"300 (150)","Invuln":"-","Armor":"-","Airborne":"Until Land (FKD)","Juggle_Start":"-","Juggle_Increase":"-","Juggle_Limit":"-","Notes":"During forward jump only; can input follow-up on hit only; puts opponent into limited juggle state (lower connect allows better follow-up juggles); button strength does not affect trajectory","Chip":"100"},{"input":"j.214K~K","Damage":"300x2,600 (1200)","Startup":"6","Active":"4(4)4(17)4","Recovery":"23(29)12 land","Total":"77","Hit_Adv":"KD 28(33)","Block_Adv":"-","Guard":"-","Cancel":"-","Hitconfirm":"-","Dmg_Scaling":"-","Punish_Adv":"KD 28(33)","PerfParry_Adv":"-","DR_Cancel_onHit":null,"DR_Cancel_onBlock":null,"Hitstun":null,"Blockstun":"-","Hitstop":"2,3,10","DriveDmg_Block":"-","DriveDmg_Hit[PC]":"-","Drive_Gain":"600x3","SuperGain_Hit":"200x3 (140x3)","SuperGain_Block":"-","Invuln":"-","Armor":"-","Airborne":"Until Land (FKD)","Juggle_Start":"-","Juggle_Increase":"-","Juggle_Limit":"-","Notes":"Comes out on hit only; can delay the input to get better KD Advantage; no follow-up after juggle state; Juri is in a crouching state during landing recovery; total recovery time before landing varies by juggle height","Chip":"-"},{"input":"j.214KK","Damage":"300","Startup":"16","Active":"until landing","Recovery":"18 land","Total":"-","Hit_Adv":"KD 37(44)","Block_Adv":"-10(-3)","Guard":"LH","Cancel":"-","Hitconfirm":"-","Dmg_Scaling":"-","Punish_Adv":"KD 37(44)","PerfParry_Adv":"-24(-17)","DR_Cancel_onHit":null,"DR_Cancel_onBlock":null,"Hitstun":null,"Blockstun":"16","Hitstop":"5","DriveDmg_Block":"3000","DriveDmg_Hit[PC]":"[5000]","Drive_Gain":"-20000","SuperGain_Hit":"600 (420)","SuperGain_Block":"300 (150)","Invuln":"-","Armor":"-","Airborne":"Until Land (FKD)","Juggle_Start":"-","Juggle_Increase":"-","Juggle_Limit":"-","Notes":"During forward jump only; can input follow-up on hit only; puts opponent into limited juggle state","Chip":"75"},{"input":"j.214KK~K","Damage":"300x3 (900)","Startup":"6","Active":"4(4)4(17)4","Recovery":"27(34)7 land","Total":"77","Hit_Adv":"KD 50(57)","Block_Adv":"-","Guard":"-","Cancel":"-","Hitconfirm":"-","Dmg_Scaling":"-","Punish_Adv":"KD 50(57)","PerfParry_Adv":"-","DR_Cancel_onHit":null,"DR_Cancel_onBlock":null,"Hitstun":null,"Blockstun":"-","Hitstop":"2,2,12","DriveDmg_Block":"-","DriveDmg_Hit[PC]":"-","Drive_Gain":"-","SuperGain_Hit":"200x3 (140x3)","SuperGain_Block":"-","Invuln":"-","Armor":"-","Airborne":"Until Land (FKD)","Juggle_Start":"-","Juggle_Increase":"1","Juggle_Limit":"-","Notes":"Puts opponent into limited juggle state; comes out on hit only; can delay the input to get better juggle follow-ups and better KD Adv.; Juri is in a crouching state during landing recovery; total recovery time before landing varies by juggle height","Chip":"-"},{"input":"236HK","Damage":null,"Startup":null,"Active":null,"Recovery":null,"Total":null,"Hit_Adv":null,"Block_Adv":null,"Guard":null,"Cancel":null,"Hitconfirm":null,"Dmg_Scaling":"-","Punish_Adv":"KD 37","PerfParry_Adv":"-28","DR_Cancel_onHit":null,"DR_Cancel_onBlock":null,"Hitstun":null,"Blockstun":"34 total","Hitstop":"4,12 (6,14)","DriveDmg_Block":"2500x2","DriveDmg_Hit[PC]":"[2500x2]","Drive_Gain":"1000x2","SuperGain_Hit":"400,300 (280,210)","SuperGain_Block":"200,150 (100,75)","Invuln":null,"Armor":null,"Airborne":null,"Juggle_Start":null,"Juggle_Increase":null,"Juggle_Limit":null,"Notes":"Costs 1 Fuha stock; both hits are Super cancelable; can press LK or MK to cancel into other 236K specials for 1 Fuha stock; puts opponent into limited juggle state (only airborne hit launches high enough for follow-up juggle besides SA3 cancel); good for damage when comboing into SA3","Chip":"175,125 (300)"},{"input":"236HK","Damage":null,"Startup":null,"Active":null,"Recovery":null,"Total":null,"Hit_Adv":null,"Block_Adv":null,"Guard":null,"Cancel":null,"Hitconfirm":null,"Dmg_Scaling":null,"Punish_Adv":null,"PerfParry_Adv":null,"DR_Cancel_onHit":null,"DR_Cancel_onBlock":null,"Hitstun":null,"Blockstun":null,"Hitstop":null,"DriveDmg_Block":null,"DriveDmg_Hit[PC]":null,"Drive_Gain":null,"SuperGain_Hit":null,"SuperGain_Block":null,"Invuln":"-","Armor":"-","Airborne":"-","Juggle_Start":"-","Juggle_Increase":"-","Juggle_Limit":"-","Notes":null,"Chip":null},{"input":"236236K","Damage":"1800","Startup":"7","Active":"-","Recovery":"201 total","Total":"201","Hit_Adv":"KD 26(49)","Block_Adv":"-32","Guard":"LH","Cancel":null,"Hitconfirm":null,"Dmg_Scaling":"30% Minimum","Punish_Adv":"KD 26(49)","PerfParry_Adv":"-51","DR_Cancel_onHit":null,"DR_Cancel_onBlock":null,"Hitstun":null,"Blockstun":"54,46,30","Hitstop":"3,6,6,8,6,10","DriveDmg_Block":"500,400x5 (2500)","DriveDmg_Hit[PC]":"800x5,1000 (5000)","Drive_Gain":null,"SuperGain_Hit":"-10000","SuperGain_Block":"-10000","Invuln":"1 Full, 2-8 Strike\/Throw","Armor":"Break","Airborne":"-","Juggle_Start":"-","Juggle_Increase":"-","Juggle_Limit":"-","Notes":"Projectile hitbox; active frames and KD Adv. are highly variable based on screen position; Full Dmg distribution: 200x4,300,700","Chip":"83x5,85 (500)"},{"input":"236236[K]","Damage":"2100","Startup":"7","Active":"-","Recovery":"200 Total","Total":"200","Hit_Adv":"KD 27(50)","Block_Adv":"-31","Guard":"LH","Cancel":null,"Hitconfirm":null,"Dmg_Scaling":"30% Minimum","Punish_Adv":"KD 27(50)","PerfParry_Adv":"-50","DR_Cancel_onHit":null,"DR_Cancel_onBlock":null,"Hitstun":null,"Blockstun":"54,46,30","Hitstop":"3,6,6,8,6,10","DriveDmg_Block":"500,400x5 (2500)","DriveDmg_Hit[PC]":"800x5,1000 (5000)","Drive_Gain":null,"SuperGain_Hit":"-10000","SuperGain_Block":"-10000","Invuln":"1 Full, 2-8 Strike\/Throw","Armor":"Break","Airborne":"-","Juggle_Start":"-","Juggle_Increase":"-","Juggle_Limit":"-","Notes":"Projectile hitbox; requires one Fuha stock to use (consumes this stock); active frames and KD Adv. are highly variable based on screen position; Full Dmg distribution: 200x4,300,1200","Chip":"83x5,85 (500)"},{"input":"214214P","Damage":"-","Startup":"1","Active":"[600]","Recovery":"6","Total":"7","Hit_Adv":"-","Block_Adv":"-","Guard":"-","Cancel":null,"Hitconfirm":null,"Dmg_Scaling":"-","Punish_Adv":"-","PerfParry_Adv":"-","DR_Cancel_onHit":null,"DR_Cancel_onBlock":null,"Hitstun":null,"Blockstun":"-","Hitstop":"-","DriveDmg_Block":"-","DriveDmg_Hit[PC]":"-","Drive_Gain":null,"SuperGain_Hit":"-20000","SuperGain_Block":"-20000","Invuln":"-","Armor":"-","Airborne":"-","Juggle_Start":"-","Juggle_Increase":"-","Juggle_Limit":"-","Notes":"Lasts 600 frames (10 seconds); timer stops counting down during attack hit\/block freeze; allows Juri to chain into normals of equal or ascending strength (cannot chain back into the same attack); chains change the properties of certain moves (6MK and Heavy normals become knockdowns); 5HK\/2LK\/2HK\/6MK become cancelable","Chip":"-"},{"input":"214214[P]","Damage":"300","Startup":"9","Active":"11","Recovery":"26","Total":"45","Hit_Adv":"-4(6)","Block_Adv":"-17(-7)","Guard":"LH","Cancel":null,"Hitconfirm":null,"Dmg_Scaling":"40% Minimum","Punish_Adv":"0(10)","PerfParry_Adv":"-33(-25)","DR_Cancel_onHit":null,"DR_Cancel_onBlock":null,"Hitstun":null,"Blockstun":"20","Hitstop":"10","DriveDmg_Block":"5000","DriveDmg_Hit[PC]":"10000","Drive_Gain":null,"SuperGain_Hit":"-20000","SuperGain_Block":"-20000","Invuln":"-","Armor":"Break","Airborne":"-","Juggle_Start":"0","Juggle_Increase":"0","Juggle_Limit":"-","Notes":"Holding the button performs a dash attack; puts airborne opponents into free juggle state or maintains existing juggle state; can cancel on hit\/block into any normal; afterwards, has same properties as regular Feng Shui Engine activation; dash attack cannot hit cross-up","Chip":"75"},{"input":"214214K","Damage":"4000","Startup":"10","Active":"4","Recovery":"52","Total":"65","Hit_Adv":"HKD 22","Block_Adv":"-31","Guard":"LH","Cancel":null,"Hitconfirm":null,"Dmg_Scaling":"50% Minimum; 10% Immediate (Sp)","Punish_Adv":"HKD 22","PerfParry_Adv":"-54","DR_Cancel_onHit":null,"DR_Cancel_onBlock":null,"Hitstun":null,"Blockstun":"25","Hitstop":"17","DriveDmg_Block":"7500","DriveDmg_Hit[PC]":"15000","Drive_Gain":null,"SuperGain_Hit":"-30000","SuperGain_Block":"-30000","Invuln":"1-13 Full","Armor":"Break","Airborne":"-","Juggle_Start":"-","Juggle_Increase":"-","Juggle_Limit":"-","Notes":"Cinematic time regenerates ~2 Drive bars for Juri","Chip":"1000"},{"input":"214214K_CA","Damage":"4500","Startup":"10","Active":"4","Recovery":"52","Total":"65","Hit_Adv":"HKD 20","Block_Adv":"-31","Guard":"LH","Cancel":null,"Hitconfirm":null,"Dmg_Scaling":"50% Minimum; 10% Immediate (Sp)","Punish_Adv":"HKD 20","PerfParry_Adv":"-54","DR_Cancel_onHit":null,"DR_Cancel_onBlock":null,"Hitstun":null,"Blockstun":"25","Hitstop":"17","DriveDmg_Block":null,"DriveDmg_Hit[PC]":null,"Drive_Gain":null,"SuperGain_Hit":null,"SuperGain_Block":null,"Invuln":"1-13 Full","Armor":"Break","Airborne":"-","Juggle_Start":"-","Juggle_Increase":"-","Juggle_Limit":"-","Notes":null,"Chip":"1250"},{"input":"214214K_CA","Damage":null,"Startup":null,"Active":null,"Recovery":null,"Total":null,"Hit_Adv":null,"Block_Adv":null,"Guard":null,"Cancel":null,"Hitconfirm":null,"Dmg_Scaling":null,"Punish_Adv":null,"PerfParry_Adv":null,"DR_Cancel_onHit":null,"DR_Cancel_onBlock":null,"Hitstun":null,"Blockstun":null,"Hitstop":null,"DriveDmg_Block":"10000","DriveDmg_Hit[PC]":"20000","Drive_Gain":null,"SuperGain_Hit":"-30000","SuperGain_Block":"-30000","Invuln":null,"Armor":null,"Airborne":null,"Juggle_Start":null,"Juggle_Increase":null,"Juggle_Limit":null,"Notes":"Available at 25% HP or below; cinematic time regenerates ~2.4 Drive bars for Juri","Chip":null}]